my_mcp_project/__init__.py
my_mcp_project/main.py
my_mcp_project-0.0.1.dist-info/METADATA
my_mcp_project-0.0.1.dist-info/WHEEL
my_mcp_project-0.0.1.dist-info/top_level.txt
my_mcp_project-0.0.1.dist-info/RECORD
