Metadata-Version: 2.4
Name: my_mcp_project
Version: 0.0.1
Summary: Exercise of TH. A small example package for MCP
Home-page: https://github.com/yourusername/my_mcp_project
Author: TH
Author-email: 360004842@qq.com
Requires-Python: >=3.10
Requires-Dist: mcp[cli]
Dynamic: author
Dynamic: author-email
Dynamic: description
Dynamic: description-content-type
Dynamic: home-page
Dynamic: requires-dist
Dynamic: requires-python
Dynamic: summary
